README
setup.py
lmi/__init__.py
lmi/base/BaseConfiguration.py
lmi/base/__init__.py
lmi/base/singletonmixin.py
lmi/providers/ComputerSystem.py
lmi/providers/IndicationManager.py
lmi/providers/JobManager.py
lmi/providers/TimerManager.py
lmi/providers/__init__.py
lmi/providers/cmpi_logging.py
openlmi.egg-info/PKG-INFO
openlmi.egg-info/SOURCES.txt
openlmi.egg-info/dependency_links.txt
openlmi.egg-info/namespace_packages.txt
openlmi.egg-info/requires.txt
openlmi.egg-info/top_level.txt