Metadata-Version: 1.1
Name: openlmi
Version: 0.4.1
Summary: OpenLMI python providers
Home-page: https://fedorahosted.org/openlmi/
Author: Michal Minar
Author-email: miminar@redhat.com
License: LGPLv2+
Platform: UNKNOWN
Classifier: License :: OSI Approved :: GNU Lesser General Public License v2 or later (LGPLv2+)
Classifier: Operating System :: POSIX :: Linux
Classifier: Topic :: System :: Systems Administration
